parsli/__init__.py
parsli/assets/__init__.py
parsli/assets/africa-cil-euclidean.vtp
parsli/assets/africa-cil-spherical.vtp
parsli/assets/asia-cil-euclidean.vtp
parsli/assets/asia-cil-spherical.vtp
parsli/assets/europe-cil-euclidean.vtp
parsli/assets/europe-cil-spherical.vtp
parsli/assets/namer-cil-euclidean.vtp
parsli/assets/namer-cil-spherical.vtp
parsli/assets/samer-cil-euclidean.vtp
parsli/assets/samer-cil-spherical.vtp
parsli/io/__init__.py
parsli/io/coast.py
parsli/io/mesh.py
parsli/io/rivers.py
parsli/io/segment.py
parsli/io/topo.py
parsli/player/__init__.py
parsli/player/app.py
parsli/tools/__init__.py
parsli/tools/topo.py
parsli/tools/wdb.py
parsli/utils/__init__.py
parsli/utils/core.py
parsli/utils/earth.py
parsli/utils/source.py
parsli/viewer/__init__.py
parsli/viewer/__main__.py
parsli/viewer/core.py
parsli/viewer/export.py
parsli/viewer/presets.json
parsli/viewer/ui.py
parsli/viewer/vtk.py
parsli/viewer/css/__init__.py
parsli/viewer/css/serve/core.css
parsli-1.2.5.dist-info/METADATA
parsli-1.2.5.dist-info/WHEEL
parsli-1.2.5.dist-info/entry_points.txt
parsli-1.2.5.dist-info/licenses/LICENSE
parsli-1.2.5.dist-info/RECORD
