Metadata-Version: 2.4
Name: parsli
Version: 1.2.5
Summary: Parsli is a VTK+trame based viewer for fault system kinematics that enables fast exploration and export of time animation.
Project-URL: Homepage, https://github.com/brendanjmeade/parsli
Project-URL: Bug Tracker, https://github.com/brendanjmeade/parsli/issues
Project-URL: Discussions, https://github.com/brendanjmeade/parsli/discussions
Project-URL: Changelog, https://github.com/brendanjmeade/parsli/releases
Author-email: Brendan Meade <brendanjmeade@gmail.com>, Sebastien Jourdain <sebastien.jourdain@kitware.com>
License-File: LICENSE
Classifier: Development Status :: 5 - Production/Stable
Classifier: Intended Audience :: Developers
Classifier: Intended Audience :: Science/Research
Classifier: License :: OSI Approved :: MIT License
Classifier: Operating System :: OS Independent
Classifier: Programming Language :: Python
Classifier: Programming Language :: Python :: 3
Classifier: Topic :: Scientific/Engineering
Requires-Python: >=3.9
Requires-Dist: h5py
Requires-Dist: pyproj
Requires-Dist: pyyaml
Requires-Dist: trame-components
Requires-Dist: trame-vtk
Requires-Dist: trame-vtklocal>=0.7
Requires-Dist: trame-vuetify
Requires-Dist: trame>=3.10
Requires-Dist: vtk>=9.4.1
Provides-Extra: app
Requires-Dist: pywebview; extra == 'app'
Provides-Extra: dev
Requires-Dist: nox; extra == 'dev'
Requires-Dist: pre-commit; extra == 'dev'
Requires-Dist: pytest-cov>=3; extra == 'dev'
Requires-Dist: pytest>=6; extra == 'dev'
Requires-Dist: ruff; extra == 'dev'
Provides-Extra: docs
Requires-Dist: furo>=2023.08.17; extra == 'docs'
Requires-Dist: myst-parser>=0.13; extra == 'docs'
Requires-Dist: sphinx-autodoc-typehints; extra == 'docs'
Requires-Dist: sphinx-copybutton; extra == 'docs'
Requires-Dist: sphinx>=7.0; extra == 'docs'
Provides-Extra: test
Requires-Dist: nox; extra == 'test'
Requires-Dist: pytest-cov>=3; extra == 'test'
Requires-Dist: pytest>=6; extra == 'test'
